Metadata-Version: 2.0
Name: pyes-fatisar
Version: 5.0.0
Summary: Python Elastic Search driver
Home-page: http://github.com/aparo/pyes/
Author: Alberto Paro
Author-email: alberto.paro@gmail.com
License: BSD
Platform: any
Classifier: Development Status :: 2 - Pre-Alpha
Classifier: Intended Audience :: Developers
Classifier: License :: OSI Approved :: BSD License
Classifier: Operating System :: OS Independent
Classifier: Programming Language :: Python
Classifier: Topic :: Internet :: WWW/HTTP :: Indexing/Search
Requires-Dist: six (>=1.5.2)
Requires-Dist: urllib3 (>=1.7)
